{
  "settings": {
    "color": {
      "gradients": [
        {
          "gradient": "radial-gradient(at 0% 0%, hsla(215,100%,95%,1) 0px, transparent 50%), radial-gradient(at 20% 0%, hsla(183,100%,93%,1) 0px, transparent 50%), radial-gradient(at 40% 0%, hsla(213,100%,84%,1) 0px, transparent 50%), radial-gradient(at 60% 0%, hsla(214,100%,93%,1) 0px, transparent 50%), radial-gradient(at 80% 0%, hsla(258,100%,94%,1) 0px, transparent 50%), radial-gradient(at 100% 0%, hsla(42,100%,89%,1) 0px, transparent 50%)",
          "name": "ProLooks Rainbow",
          "slug": "prolooks-rainbow"
        },
        {
          "gradient": "radial-gradient(at 100% 100%, hsla(288,0%,100%,1) 0px, transparent 50%), radial-gradient(at 41% 85%, hsla(148,0%,100%,1) 0px, transparent 50%), radial-gradient(at 56% 36%, hsla(311,100%,100%,1) 0px, transparent 50%), radial-gradient(at 72% 61%, hsla(201,100%,90%,1) 0px, transparent 50%), radial-gradient(at 33% 38%, hsla(201,74%,92%,1) 0px, transparent 50%), radial-gradient(at 80% 47%, hsla(284,87%,94%,1) 0px, transparent 50%), radial-gradient(at 27% 54%, hsla(20,92%,91%,1) 0px, transparent 50%)",
          "name": "ProLooks Mesh Gradient",
          "slug": "prolooks-mesh"
        }
      ],
      "palette": [
				{
          "color": "#012E29",
          "name": "Brand",
          "slug": "brand"
        },
        {
          "color": "#315835",
          "name": "Brand 2",
          "slug": "brand-2"
        },
        {
          "color": "#456A49",
          "name": "Brand 3",
          "slug": "brand-3"
        },
        {
          "color": "#EEF7F0",
          "name": "Brand 4",
          "slug": "brand-4"
        },
        {
          "color": "#F7FCF8",
          "name": "Brand 5",
          "slug": "brand-5"
        },
        {
          "color": "#FCFFFD",
          "name": "Brand 6",
          "slug": "brand-6"
        },
        {
          "color": "#ffffff",
          "name": "Base",
          "slug": "base"
        },
        {
          "color": "#FBFAF8",
          "name": "Base 2",
          "slug": "base-2"
        },
        {
          "color": "#F6F4F1",
          "name": "Base 3",
          "slug": "base-3"
        },
        {
          "color": "#EDE8E6",
          "name": "Base 4",
          "slug": "base-4"
        },
        {
          "color": "#E5DFDC",
          "name": "Base 5",
          "slug": "base-5"
        },
        {
          "color": "#D9D3D0",
          "name": "Base 6",
          "slug": "base-6"
        },
        {
          "color": "#1B1B1A",
          "name": "Contrast",
          "slug": "contrast"
        },
        {
          "color": "#30302F",
          "name": "Contrast 2",
          "slug": "contrast-2"
        },
        {
          "color": "#4B4A49",
          "name": "Contrast 3",
          "slug": "contrast-3"
        },
        {
          "color": "#6F6D6C",
          "name": "Contrast 4",
          "slug": "contrast-4"
        },
        {
          "color": "#8F8D8B",
          "name": "Contrast 5",
          "slug": "contrast-5"
        },
        {
          "color": "#AEABA9",
          "name": "Contrast 6",
          "slug": "contrast-6"
        }
      ]
    }
  },
  "version": 3,
  "$schema": "https://schemas.wp.org/trunk/theme.json",
	"title": "Parsley",
	"slug": "color-parsley"
}
